reactpy_html_string_compiler/__init__.py
reactpy_html_string_compiler/main.py
reactpy_html_string_compiler-0.3.0.dist-info/METADATA
reactpy_html_string_compiler-0.3.0.dist-info/WHEEL
reactpy_html_string_compiler-0.3.0.dist-info/top_level.txt
reactpy_html_string_compiler-0.3.0.dist-info/RECORD
