Metadata-Version: 2.1
Name: reactpy_html_string_compiler
Version: 0.3.0
Summary: compiles reactpy components into html string
Classifier: Programming Language :: Python :: 3
Classifier: License :: OSI Approved :: MIT License
Classifier: Operating System :: OS Independent
Requires-Python: >=3.6
Requires-Dist: reactpy >=1.0.1
